godaddycheck/__init__.py
godaddycheck/cli.py
godaddycheck/client.py
godaddycheck-0.1.4.dist-info/licenses/LICENSE
godaddycheck-0.1.4.dist-info/METADATA
godaddycheck-0.1.4.dist-info/WHEEL
godaddycheck-0.1.4.dist-info/entry_points.txt
godaddycheck-0.1.4.dist-info/top_level.txt
godaddycheck-0.1.4.dist-info/RECORD
