Metadata-Version: 2.4
Name: godaddycheck
Version: 0.1.4
Summary: Simple GoDaddy domain availability checker
Author-email: Aman <hi@amankumar.ai>
License: MIT
Project-URL: Homepage, https://github.com/onlyoneaman/godaddycheck
Project-URL: Repository, https://github.com/onlyoneaman/godaddycheck
Project-URL: Issues, https://github.com/onlyoneaman/godaddycheck/issues
Keywords: godaddy,domain,availability,checker,dns
Classifier: Development Status :: 3 - Alpha
Classifier: Intended Audience :: Developers
Classifier: License :: OSI Approved :: MIT License
Classifier: Programming Language :: Python :: 3
Classifier: Programming Language :: Python :: 3.7
Classifier: Programming Language :: Python :: 3.8
Classifier: Programming Language :: Python :: 3.9
Classifier: Programming Language :: Python :: 3.10
Classifier: Programming Language :: Python :: 3.11
Classifier: Programming Language :: Python :: 3.12
Requires-Python: >=3.7
License-File: LICENSE
Requires-Dist: httpx>=0.24.0
Requires-Dist: python-dotenv>=1.0.0
Provides-Extra: dev
Requires-Dist: pytest>=7.0.0; extra == "dev"
Requires-Dist: pytest-cov>=4.0.0; extra == "dev"
Dynamic: license-file
